digitalriver/__init__.py
digitalriver/main.py
digitalriver/controllers/__init__.py
digitalriver/controllers/base.py
digitalriver/controllers/droplet.py
digitalriver/controllers/provision.py
digitalriver/models/__init__.py
digitalriver/models/base.py
digitalriver/models/feature.py
digitalriver/models/instance.py
digitalriver/models/provision.py
digitalriver/util/__init__.py
digitalriver/util/deployer.py
digitalriver/static/css/layout.css
digitalriver/static/images/favicon.ico
digitalriver/static/images/login.png
digitalriver/static/images/logo-footer.png
digitalriver/static/js/main.js
digitalriver/templates/about.html.tpl
digitalriver/templates/index.html.tpl
digitalriver/templates/signin.html.tpl
digitalriver/templates/droplet/config.html.tpl
digitalriver/templates/droplet/features.html.tpl
digitalriver/templates/droplet/list.html.tpl
digitalriver/templates/droplet/provision.html.tpl
digitalriver/templates/droplet/show.html.tpl
digitalriver/templates/partials/layout.html.tpl
digitalriver/templates/partials/layout_droplet.html.tpl
digitalriver/templates/partials/layout_provision.html.tpl
digitalriver/templates/partials/layout_simple.html.tpl
digitalriver/templates/provision/list.html.tpl
digitalriver/templates/provision/log.html.tpl
digitalriver/templates/provision/show.html.tpl
digitalriver-0.1.4.dist-info/top_level.txt
digitalriver-0.1.4.dist-info/METADATA
digitalriver-0.1.4.dist-info/DESCRIPTION.rst
digitalriver-0.1.4.dist-info/metadata.json
digitalriver-0.1.4.dist-info/WHEEL
digitalriver-0.1.4.dist-info/RECORD
